odoo/addons/base_user_effective_permissions/=
odoo/addons/base_user_effective_permissions/README.rst
odoo/addons/base_user_effective_permissions/__init__.py
odoo/addons/base_user_effective_permissions/__manifest__.py
odoo/addons/base_user_effective_permissions/i18n/base_user_effective_permissions.pot
odoo/addons/base_user_effective_permissions/i18n/it.po
odoo/addons/base_user_effective_permissions/models/__init__.py
odoo/addons/base_user_effective_permissions/models/res_users.py
odoo/addons/base_user_effective_permissions/models/res_users_effective_permission.py
odoo/addons/base_user_effective_permissions/readme/CONTRIBUTORS.rst
odoo/addons/base_user_effective_permissions/readme/DESCRIPTION.rst
odoo/addons/base_user_effective_permissions/readme/USAGE.rst
odoo/addons/base_user_effective_permissions/security/ir.model.access.csv
odoo/addons/base_user_effective_permissions/static/description/icon.png
odoo/addons/base_user_effective_permissions/static/description/index.html
odoo/addons/base_user_effective_permissions/tests/__init__.py
odoo/addons/base_user_effective_permissions/tests/test_base_user_effective_permissions.py
odoo/addons/base_user_effective_permissions/views/res_users.xml
odoo/addons/base_user_effective_permissions/views/res_users_effective_permission.xml
odoo_addon_base_user_effective_permissions-16.0.1.0.0.4.dist-info/METADATA
odoo_addon_base_user_effective_permissions-16.0.1.0.0.4.dist-info/WHEEL
odoo_addon_base_user_effective_permissions-16.0.1.0.0.4.dist-info/top_level.txt
odoo_addon_base_user_effective_permissions-16.0.1.0.0.4.dist-info/RECORD
