Metadata-Version: 2.1
Name: odoo-addon-base_user_effective_permissions
Version: 16.0.1.0.0.4
Summary: Inspect effective permissions applying to a user
Home-page: https://github.com/OCA/server-backend
Author: Hunki Enterprises BV, Odoo Community Association (OCA)
Author-email: support@odoo-community.org
License: AGPL-3
Classifier: Programming Language :: Python
Classifier: Framework :: Odoo
Classifier: Framework :: Odoo :: 16.0
Classifier: License :: OSI Approved :: GNU Affero General Public License v3
Classifier: Development Status :: 3 - Alpha
Requires-Python: >=3.10
Requires-Dist: odoo<16.1dev,>=16.0a
